drylib/__init__.py
drylib-0.0.1.dist-info/METADATA
drylib-0.0.1.dist-info/UNLICENSE
drylib-0.0.1.dist-info/WHEEL
drylib-0.0.1.dist-info/top_level.txt
drylib-0.0.1.dist-info/RECORD
