Metadata-Version: 2.1
Name: drylib
Version: 0.0.1
Summary: DRYlib for Python
Home-page: https://drylib.org/python.html
Author: Arto Bendiken
Author-email: arto@dryproject.org
License: Public Domain
Project-URL: Source, https://github.com/dryproject/drylib.py
Keywords: drylib polyglot
Platform: UNKNOWN
Classifier: Development Status :: 2 - Pre-Alpha
Classifier: Environment :: Console
Classifier: Intended Audience :: Developers
Classifier: Intended Audience :: Information Technology
Classifier: Intended Audience :: Science/Research
Classifier: License :: Public Domain
Classifier: Natural Language :: English
Classifier: Operating System :: OS Independent
Classifier: Programming Language :: Python :: 3 :: Only
Classifier: Programming Language :: Python :: 3.5
Classifier: Programming Language :: Python :: 3.6
Classifier: Programming Language :: Python :: 3.7
Classifier: Topic :: Scientific/Engineering :: Mathematics
Classifier: Topic :: Software Development :: Libraries
Classifier: Topic :: Text Processing :: General
Requires-Python: ~=3.5
Provides-Extra: test
Requires-Dist: pytest; extra == 'test'
